mypackage/__init__.py
mypackage/main.py
packaging_tutorial_jilejiafle-0.1.dist-info/METADATA
packaging_tutorial_jilejiafle-0.1.dist-info/WHEEL
packaging_tutorial_jilejiafle-0.1.dist-info/top_level.txt
packaging_tutorial_jilejiafle-0.1.dist-info/RECORD
