Metadata-Version: 2.1
Name: packaging-tutorial-jilejiafle
Version: 0.1
Summary: A small example package
Home-page: https://github.com/youhs4554/packaging_tutorial.git
Author: hossay
Author-email: youhs4554@gmail.com
License: UNKNOWN
Download-URL: https://github.com/youhs4554/packaging_tutorial/archive/refs/tags/v0.1.tar.gz
Keywords: tootorch,XAI
Platform: UNKNOWN
Classifier: Programming Language :: Python :: 3
Classifier: Programming Language :: Python :: 3.6
Classifier: Programming Language :: Python :: 3.7
Classifier: Topic :: Scientific/Engineering :: Artificial Intelligence
Classifier: Topic :: Software Development :: Libraries :: Python Modules
Requires-Python: >=3.6
Requires-Dist: torch
